rbc_pdf_statement_parser/__init__.py
rbc_pdf_statement_parser/__main__.py
rbc_pdf_statement_parser/cli.py
rbc_pdf_statement_parser/convert_all_to_table.py
rbc_pdf_statement_parser/convert_all_to_text.py
rbc_pdf_statement_parser/move_all_to_renamed_folder.py
rbc_pdf_statement_parser/util.py
rbc_pdf_statement_parser-0.1.1.dist-info/METADATA
rbc_pdf_statement_parser-0.1.1.dist-info/WHEEL
rbc_pdf_statement_parser-0.1.1.dist-info/entry_points.txt
rbc_pdf_statement_parser-0.1.1.dist-info/licenses/LICENSE
rbc_pdf_statement_parser-0.1.1.dist-info/RECORD
