Metadata-Version: 2.3
Name: rbc_pdf_statement_parser
Version: 0.1.1
Summary: A Python-based parser for RBC Business Account statements
Project-URL: homepage, https://github.com/DeflateAwning/rbc-pdf-statement-parser
Project-URL: repository, https://github.com/DeflateAwning/rbc-pdf-statement-parser
Project-URL: issues, https://github.com/DeflateAwning/rbc-pdf-statement-parser/issues
Project-URL: license, https://github.com/DeflateAwning/rbc-pdf-statement-parser/blob/main/LICENSE
Author: DeflateAwning
License-Expression: Unlicense
License-File: LICENSE
Classifier: License :: OSI Approved :: The Unlicense (Unlicense)
Classifier: Operating System :: OS Independent
Classifier: Programming Language :: Python :: 3
Requires-Dist: jpype1
Requires-Dist: orjson
Requires-Dist: pandas
Requires-Dist: polars
Requires-Dist: pyarrow
Requires-Dist: pymupdf
Requires-Dist: tabula-py
